expense_manager_library/__init__.py
expense_manager_library/data_cleaner.py
expense_manager_library/report_generator.py
expense_manager_library/visualizer.py
tests/__init__.py
tests/test_data_cleaner.py
tests/test_generate_report.py
tests/test_save_report_to_pdf.py
tests/test_visualizer.py
expense_manager_library-3.0.0.dist-info/LICENSE
expense_manager_library-3.0.0.dist-info/METADATA
expense_manager_library-3.0.0.dist-info/WHEEL
expense_manager_library-3.0.0.dist-info/top_level.txt
expense_manager_library-3.0.0.dist-info/RECORD
