Metadata-Version: 2.1
Name: expense_manager_library
Version: 3.0.0
Summary: A library to analyze expense data and generate PDF reports.
Home-page: https://github.com/berry24a/expense_manager_library
Classifier: Programming Language :: Python :: 3
Classifier: License :: OSI Approved :: MIT License
Classifier: Operating System :: OS Independent
Requires-Python: >=3.8
License-File: LICENSE
Requires-Dist: pandas>=1.3.5
Requires-Dist: matplotlib>=3.5.1
